macc/__init__.py
macc/_modidx.py
macc/datasets.py
macc/learn.py
macc-0.0.1.dist-info/LICENSE
macc-0.0.1.dist-info/METADATA
macc-0.0.1.dist-info/WHEEL
macc-0.0.1.dist-info/entry_points.txt
macc-0.0.1.dist-info/top_level.txt
macc-0.0.1.dist-info/RECORD
