Metadata-Version: 2.1
Name: macc
Version: 0.0.1
Summary: mini accelerator
Home-page: https://github.com/niyazikemer/macc
Author: niyazikemer
Author-email: nkemer@gmail.com
License: Apache Software License 2.0
Keywords: nbdev jupyter notebook python
Classifier: Development Status :: 4 - Beta
Classifier: Intended Audience :: Developers
Classifier: Natural Language :: English
Classifier: Programming Language :: Python :: 3.7
Classifier: Programming Language :: Python :: 3.8
Classifier: Programming Language :: Python :: 3.9
Classifier: Programming Language :: Python :: 3.10
Classifier: License :: OSI Approved :: Apache Software License
Requires-Python: >=3.7
License-File: LICENSE
Requires-Dist: fastcore
Requires-Dist: torch
Requires-Dist: fastprogress
Requires-Dist: matplotlib
Requires-Dist: numpy
Requires-Dist: datasets
Requires-Dist: torchvision
Requires-Dist: torcheval
Provides-Extra: dev
